AUTHORS.rst
CONTRIBUTING.rst
HISTORY.rst
LICENSE
MANIFEST.in
README.rst
setup.cfg
setup.py
parrot_integrations/.DS_Store
parrot_integrations/bigquery/__init__.py
parrot_integrations/bigquery/insert.py
parrot_integrations/bigquery/query.py
parrot_integrations/gcs/__init__.py
parrot_integrations_gcp.egg-info/PKG-INFO
parrot_integrations_gcp.egg-info/SOURCES.txt
parrot_integrations_gcp.egg-info/dependency_links.txt
parrot_integrations_gcp.egg-info/not-zip-safe
parrot_integrations_gcp.egg-info/requires.txt
parrot_integrations_gcp.egg-info/top_level.txt
tests/__init__.py
tests/conftest.py